pushpad/__init__.py
pushpad/notification.py
pushpad/pushpad.py
pushpad-1.0.0.dist-info/LICENSE.txt
pushpad-1.0.0.dist-info/METADATA
pushpad-1.0.0.dist-info/WHEEL
pushpad-1.0.0.dist-info/top_level.txt
pushpad-1.0.0.dist-info/RECORD
