Metadata-Version: 2.1
Name: pushpad
Version: 1.0.0
Summary: Pushpad: real push notifications for websites
Home-page: https://pushpad.xyz
Author: Pushpad
Author-email: support@pushpad.xyz
License: MIT
Keywords: pushpad web push notifications api
Classifier: Intended Audience :: Developers
Classifier: Topic :: Software Development :: Libraries
Classifier: License :: OSI Approved :: MIT License
Classifier: License :: OSI Approved :: MIT License
Classifier: Programming Language :: Python :: 2
Classifier: Programming Language :: Python :: 3
License-File: LICENSE.txt
Requires-Dist: requests
Provides-Extra: dev
Requires-Dist: check-manifest ; extra == 'dev'
Provides-Extra: test
Requires-Dist: coverage ; extra == 'test'
